Metadata-Version: 2.1
Name: git2gitee
Version: 0.9.6
Summary: import github repo to gitee, then clone to local
Home-page: https://github.com/toyourheart163/git2gitee
Author: Mikele
Author-email: blive200@gmail.com
License: UNKNOWN
Platform: UNKNOWN
Classifier: Programming Language :: Python :: 3
Classifier: License :: OSI Approved :: MIT License
Classifier: Operating System :: OS Independent
Requires-Python: >=3.6
